FabricFramework/DataSource.py
FabricFramework/DataValidation.py
FabricFramework/FabricConfiguration.py
FabricFramework/FabricDataInterface.py
FabricFramework/FabricFramework.py
FabricFramework/FabricLocations.py
FabricFramework/LogMonitor.py
FabricFramework/__init__.py
AntaresFabricFramework_INTERNAL-1.1.41.dist-info/LICENSE.txt
AntaresFabricFramework_INTERNAL-1.1.41.dist-info/METADATA
AntaresFabricFramework_INTERNAL-1.1.41.dist-info/WHEEL
AntaresFabricFramework_INTERNAL-1.1.41.dist-info/top_level.txt
AntaresFabricFramework_INTERNAL-1.1.41.dist-info/RECORD
