Metadata-Version: 2.1
Name: AntaresFabricFramework-INTERNAL
Version: 1.1.41
Summary: Microsoft Fabric data ingestion accelerator
Home-page: https://antares.solutions/
Author: Antares Solutions
Author-email: martonm@antaressolutions.com.au
Project-URL: Bug Tracker, https://antares.solutions/
Classifier: Programming Language :: Python :: 3
Classifier: License :: OSI Approved :: MIT License
Classifier: Operating System :: OS Independent
Requires-Python: >=3.6
License-File: LICENSE.txt
